odoo/addons/fieldservice_repair/README.rst
odoo/addons/fieldservice_repair/__init__.py
odoo/addons/fieldservice_repair/__manifest__.py
odoo/addons/fieldservice_repair/models/__init__.py
odoo/addons/fieldservice_repair/models/fsm_order.py
odoo/addons/fieldservice_repair/readme/CONFIGURE.rst
odoo/addons/fieldservice_repair/readme/CONTRIBUTORS.rst
odoo/addons/fieldservice_repair/readme/CREDITS.rst
odoo/addons/fieldservice_repair/readme/DESCRIPTION.rst
odoo/addons/fieldservice_repair/readme/INSTALL.rst
odoo/addons/fieldservice_repair/readme/ROADMAP.rst
odoo/addons/fieldservice_repair/readme/USAGE.rst
odoo/addons/fieldservice_repair/static/description/icon.png
odoo/addons/fieldservice_repair/static/description/index.html
odoo/addons/fieldservice_repair/static/description/description/icon.png
odoo/addons/fieldservice_repair/static/description/description/index.html
odoo/addons/fieldservice_repair/views/fsm_order_view.xml
odoo11_addon_fieldservice_repair-11.0.0.1.0.dist-info/METADATA
odoo11_addon_fieldservice_repair-11.0.0.1.0.dist-info/RECORD
odoo11_addon_fieldservice_repair-11.0.0.1.0.dist-info/WHEEL
odoo11_addon_fieldservice_repair-11.0.0.1.0.dist-info/top_level.txt
